dlm_matrix/__init__.py
dlm_matrix/builder.py
dlm_matrix/context.py
dlm_matrix/merger.py
dlm_matrix/processor.py
dlm_matrix/relationship.py
dlm_matrix/type.py
dlm_matrix/utils.py
dlm_matrix/callbacks/__init__.py
dlm_matrix/callbacks/agent.py
dlm_matrix/callbacks/base.py
dlm_matrix/callbacks/info.py
dlm_matrix/callbacks/manager.py
dlm_matrix/callbacks/streaming.py
dlm_matrix/chaintrees/__init__.py
dlm_matrix/chaintrees/base.py
dlm_matrix/chaintrees/factory.py
dlm_matrix/chaintrees/instruction.py
dlm_matrix/chaintrees/interface.py
dlm_matrix/chaintrees/links.py
dlm_matrix/chaintrees/symphony/__init__.py
dlm_matrix/chaintrees/symphony/builder.py
dlm_matrix/chaintrees/symphony/director.py
dlm_matrix/chaintrees/symphony/manager.py
dlm_matrix/chaintrees/symphony/system.py
dlm_matrix/chaintrees/symphony/technique.py
dlm_matrix/chaintrees/symphony/synthesis/__init__.py
dlm_matrix/chaintrees/symphony/synthesis/chaos_theory.py
dlm_matrix/chaintrees/symphony/synthesis/convergent_fusion.py
dlm_matrix/chaintrees/symphony/synthesis/divergent_expansion.py
dlm_matrix/chaintrees/symphony/synthesis/emergent_synthesis.py
dlm_matrix/chaintrees/symphony/synthesis/eureka_elicitation.py
dlm_matrix/chaintrees/symphony/synthesis/fractal_thinking.py
dlm_matrix/chaintrees/symphony/synthesis/infinite_mind.py
dlm_matrix/chaintrees/symphony/synthesis/metaphysical_illumination.py
dlm_matrix/chaintrees/symphony/synthesis/morphogenesis.py
dlm_matrix/chaintrees/symphony/synthesis/non_linear_navigation.py
dlm_matrix/chaintrees/symphony/synthesis/organic_synthesis.py
dlm_matrix/chaintrees/symphony/synthesis/paradoxical_reflection.py
dlm_matrix/chaintrees/symphony/synthesis/power_of_perspective.py
dlm_matrix/chaintrees/symphony/synthesis/quantum_entanglement.py
dlm_matrix/chaintrees/symphony/synthesis/radical_collaboration.py
dlm_matrix/chaintrees/symphony/synthesis/synergetic_fusion.py
dlm_matrix/embedding/__init__.py
dlm_matrix/embedding/base.py
dlm_matrix/embedding/helper.py
dlm_matrix-0.7.10.dist-info/LICENSE
dlm_matrix-0.7.10.dist-info/METADATA
dlm_matrix-0.7.10.dist-info/WHEEL
dlm_matrix-0.7.10.dist-info/top_level.txt
dlm_matrix-0.7.10.dist-info/RECORD
